gmail_draft_creator/__init__.py
gmail_draft_creator-1.3.1.dist-info/LICENSE
gmail_draft_creator-1.3.1.dist-info/METADATA
gmail_draft_creator-1.3.1.dist-info/WHEEL
gmail_draft_creator-1.3.1.dist-info/entry_points.txt
gmail_draft_creator-1.3.1.dist-info/RECORD
