Metadata-Version: 2.1
Name: gmail-draft-creator
Version: 1.3.1
Summary: Simple tool to take a CSV and a template and create drafts in your Gmail. Can be used as a command line tool, or as a library.
Home-page: https://github.com/iloveitaly/gmail-draft-creator
License: MIT
Keywords: gmail,email,gmail-api
Author: Michael Bianco
Author-email: mike@mikebian.co
Requires-Python: >=3.9,<4.0
Classifier: License :: OSI Approved :: MIT License
Classifier: Programming Language :: Python :: 3
Classifier: Programming Language :: Python :: 3.9
Classifier: Programming Language :: Python :: 3.10
Classifier: Programming Language :: Python :: 3.11
Requires-Dist: click (>=8.1.7,<9.0.0)
Requires-Dist: google-api-python-client (>=2.97.0,<3.0.0)
Requires-Dist: google-auth-httplib2 (>=0.1.0,<0.2.0)
Requires-Dist: google-auth-oauthlib (>=0.4.6,<0.5.0)
Requires-Dist: markdown (>=3.5.1,<4.0.0)
Requires-Dist: python-decouple (>=3.5,<4.0)
